flask_auth_service_mongo/__init__.py
flask_auth_service_mongo/config.py
flask_auth_service_mongo/constants/__init__.py
flask_auth_service_mongo/constants/enums.py
flask_auth_service_mongo/constants/responses.py
flask_auth_service_mongo/constants/security.py
flask_auth_service_mongo/security/__init__.py
flask_auth_service_mongo/security/commands.py
flask_auth_service_mongo/security/middlewares.py
flask_auth_service_mongo/security/models.py
flask_auth_service_mongo/security/repository.py
flask_auth_service_mongo/security/utils.py
flask_auth_service_mongo/security/api_rest/__init__.py
flask_auth_service_mongo/security/api_rest/session.py
flask_auth_service_mongo/security/auth/__init__.py
flask_auth_service_mongo/security/auth/decorators.py
flask_auth_service_mongo/security/auth/user.py
flask_auth_service_mongo/security/schema/__init__.py
flask_auth_service_mongo/security/schema/role.py
flask_auth_service_mongo/security/schema/session.py
flask_auth_service_mongo/security/schema/user.py
flask_auth_service_mongo/security/use_cases/__init__.py
flask_auth_service_mongo/security/use_cases/role.py
flask_auth_service_mongo/security/use_cases/session.py
flask_auth_service_mongo/security/use_cases/user.py
flask_auth_service_mongo/utils/__init__.py
flask_auth_service_mongo/utils/contract.py
flask_auth_service_mongo/utils/helpers.py
flask_auth_service_mongo/utils/schema.py
flask_auth_service_mongo/utils/use_case.py
flask_auth_service_mongo/utils/validator.py
tests/__init__.py
tests/constants/__init__.py
tests/constants/test_security.py
tests/security/__init__.py
tests/security/test_auth.py
tests/security/test_commands.py
tests/security/test_middleware.py
tests/security/test_models.py
tests/security/test_repository.py
tests/security/test_utils.py
tests/security/api_rest/__init__.py
tests/security/api_rest/test_session.py
tests/security/schema/__init__.py
tests/security/schema/test_user.py
tests/security/use_cases/__init__.py
tests/security/use_cases/test_role.py
flask_auth_service_mongo-0.1.8.dist-info/LICENSE.txt
flask_auth_service_mongo-0.1.8.dist-info/METADATA
flask_auth_service_mongo-0.1.8.dist-info/WHEEL
flask_auth_service_mongo-0.1.8.dist-info/top_level.txt
flask_auth_service_mongo-0.1.8.dist-info/RECORD
