Metadata-Version: 2.1
Name: flask-auth-service-mongo
Version: 0.1.8
Summary: Flask JWT authentication package with mongo.
Home-page: https://gitlab.com/terminus-zinobe/flask-auth-service-mongo
Author: Terminus
Author-email: mateo.chaparro@zinobe.com
License: UNKNOWN
Platform: UNKNOWN
Classifier: Programming Language :: Python :: 3
Classifier: License :: OSI Approved :: MIT License
Classifier: Operating System :: OS Independent
Requires-Python: >=3.6
Requires-Dist: bcrypt (<4,>=3)
Requires-Dist: Cerberus (<2,>=1.3)
Requires-Dist: flask (<2,>=1)
Requires-Dist: PyJWT (<2,>=1.7)
Requires-Dist: mongoengine (<0.20,>=0.18)
Requires-Dist: radon (<5,>=4)
Requires-Dist: graphene (<3,>=2.1)
Requires-Dist: graphene-mongo (<0.3,>=0.2)
